{
  "requestsFinished": 0,
  "requestsFailed": 0,
  "requestsRetries": 0,
  "requestsFailedPerMinute": 0,
  "requestsFinishedPerMinute": 0,
  "requestMinDurationMillis": null,
  "requestMaxDurationMillis": 0,
  "requestTotalFailedDurationMillis": 0,
  "requestTotalFinishedDurationMillis": 0,
  "crawlerStartedAt": "2026-01-02T21:33:28.311Z",
  "crawlerFinishedAt": "2026-01-02T21:33:28.362Z",
  "statsPersistedAt": "2026-01-02T21:33:28.362Z",
  "crawlerRuntimeMillis": 217,
  "crawlerLastStartTimestamp": 1767389608145,
  "requestRetryHistogram": [],
  "statsId": 6,
  "requestAvgFailedDurationMillis": null,
  "requestAvgFinishedDurationMillis": null,
  "requestTotalDurationMillis": 0,
  "requestsTotal": 0,
  "requestsWithStatusCode": {},
  "errors": {},
  "retryErrors": {}
}